_libcurl_cffi.abi3.so
mcurl/__init__.py
mcurl/cacert.pem
mcurl/gen.py
pymcurl.libs/libcom_err-b6a98d28.so.3.0
pymcurl.libs/libcrypto-c4e86b29.so.3
pymcurl.libs/libcurl-7b690218.so.4.8.0
pymcurl.libs/libgssapi_krb5-ff66d1b7.so.2.2
pymcurl.libs/libk5crypto-e6e0c319.so.3.1
pymcurl.libs/libkrb5-b5d4dd23.so.3.3
pymcurl.libs/libkrb5support-5ce10236.so.0.1
pymcurl.libs/libnghttp2-215f5f9e.so.14.28.3
pymcurl.libs/libssl-1b6d8164.so.3
pymcurl-8.12.1.1.dist-info/LICENSE.txt
pymcurl-8.12.1.1.dist-info/METADATA
pymcurl-8.12.1.1.dist-info/WHEEL
pymcurl-8.12.1.1.dist-info/top_level.txt
pymcurl-8.12.1.1.dist-info/RECORD
