Metadata-Version: 2.1
Name: pymcurl
Version: 8.12.1.1
Summary: Manage outbound HTTP connections using Curl & CurlMulti
Author-email: Ganesh Viswanathan <dev@genotrance.com>
Project-URL: Homepage, https://github.com/genotrance/mcurl
Project-URL: Repository, https://github.com/genotrance/mcurl
Project-URL: Issues, https://github.com/genotrance/mcurl/issues
Classifier: Development Status :: 4 - Beta
Classifier: Environment :: Win32 (MS Windows)
Classifier: Environment :: MacOS X
Classifier: Intended Audience :: Developers
Classifier: Intended Audience :: System Administrators
Classifier: License :: OSI Approved :: MIT License
Classifier: Natural Language :: English
Classifier: Operating System :: MacOS :: MacOS X
Classifier: Operating System :: Microsoft :: Windows
Classifier: Operating System :: POSIX :: Linux
Classifier: Programming Language :: Python :: 3.8
Classifier: Programming Language :: Python :: 3.9
Classifier: Programming Language :: Python :: 3.10
Classifier: Programming Language :: Python :: 3.11
Classifier: Programming Language :: Python :: 3.12
Classifier: Programming Language :: Python :: 3.13
Classifier: Topic :: Internet :: WWW/HTTP
Requires-Python: >=3.8
License-File: LICENSE.txt
Requires-Dist: cffi
